Workbook
Name SegmentaciónDeDatos_country: #N/A
Name SegmentaciónDeDatos_Icono: #N/A
Name SegmentaciónDeDatos_sector: #N/A
Name Slicer_Continente: #N/A
Name Slicer_repayment_interval: #N/A

Sheet Sheet2
A1: Row Labels | B1: Sum of loan_amount | D1: Row Labels | E1: Sum of funded_amount | G1: Row Labels | H1: Sum of paid_amount | J1: Row Labels | K1: Sum of loan_amount | M1: Row Labels | N1: Sum of funded_amount
A2: Agriculture | B2: 1907300 | D2: Agriculture | E2: 1845825 | G2: Agriculture | H2: 61475 | J2: Albania | K2: 64800 | M2: Africa | N2: 1906075
A3: Arts | B3: 208350 | D3: Arts | E3: 200960 | G3: Arts | H3: 7390 | J3: Armenia | K3: 175500 | M3: Asia | N3: 2293950
A4: Clothing | B4: 647175 | D4: Clothing | E4: 624755 | G4: Clothing | H4: 22420 | J4: Azerbaijan | K4: 94950 | M4: Central America | N4: 1133000
A5: Construction | B5: 131375 | D5: Construction | E5: 130475 | G5: Construction | H5: 900 | J5: Bolivia | K5: 321175 | M5: North America | N5: 368195
A6: Education | B6: 405850 | D6: Education | E6: 405850 | G6: Education | H6: 0 | J6: Brazil | K6: 1700 | M6: Oceania | N6: 120825
A7: Entertainment | B7: 16675 | D7: Entertainment | E7: 16675 | G7: Entertainment | H7: 0 | J7: Burkina Faso | K7: 22875 | M7: Rest of Europe | N7: 1024275
A8: Food | B8: 2119425 | D8: Food | E8: 2062025 | G8: Food | H8: 57400 | J8: Burundi | K8: 129400 | M8: South America | N8: 2029575
A9: Health | B9: 75200 | D9: Health | E9: 75200 | G9: Health | H9: 0 | J9: Cambodia | K9: 300875 | M9: Grand Total | N9: 8875895
A10: Housing | B10: 479675 | D10: Housing | E10: 446775 | G10: Housing | H10: 32900 | J10: Cameroon | K10: 21125
A11: Manufacturing | B11: 116275 | D11: Manufacturing | E11: 116275 | G11: Manufacturing | H11: 0 | J11: Chile | K11: 18475
A12: Personal Use | B12: 170050 | D12: Personal Use | E12: 162375 | G12: Personal Use | H12: 7675 | J12: Colombia | K12: 280150
A13: Retail | B13: 1773500 | D13: Retail | E13: 1712465 | G13: Retail | H13: 61035 | J13: Congo | K13: 34800
A14: Services | B14: 826475 | D14: Services | E14: 796465 | G14: Services | H14: 30010 | J14: Costa Rica | K14: 35050
A15: Transportation | B15: 307750 | D15: Transportation | E15: 269175 | G15: Transportation | H15: 38575 | J15: Dominican Republic | K15: 31650
A16: Wholesale | B16: 10925 | D16: Wholesale | E16: 10600 | G16: Wholesale | H16: 325 | J16: Ecuador | K16: 351300
A17: Grand Total | B17: 9196000 | D17: Grand Total | E17: 8875895 | G17: Grand Total | H17: 320105 | J17: El Salvador | K17: 601300
J18: Georgia | K18: 238825
J19: Ghana | K19: 42600
J20: Guatemala | K20: 58975
J21: Haiti | K21: 57850
J22: Honduras | K22: 119600
D23: Row Labels | E23: Sum of funded_amount | J23: India | K23: 184975 | M23: Row Labels | N23: Sum of funded_amount
D24: female | E24: 6434015 | J24: Indonesia | K24: 50025 | M24: bullet | N24: 548120
D25: male | E25: 2441880 | J25: Iraq | K25: 97800 | M25: irregular | N25: 2737575
D26: Grand Total | E26: 8875895 | J26: Israel | K26: 20375 | M26: monthly | N26: 5588700
J27: Jordan | K27: 133775 | M27: weekly | N27: 1500
J28: Kenya | K28: 418400 | M28: Grand Total | N28: 8875895
J29: Kosovo | K29: 23925
J30: Kyrgyzstan | K30: 106575
J31: Lebanon | K31: 25625
J32: Liberia | K32: 83900
J33: Mali | K33: 101625
J34: Mexico | K34: 55125
J35: Mongolia | K35: 141650
J36: Nepal | K36: 5100
J37: Nicaragua | K37: 242825
J38: Pakistan | K38: 207100
J39: Palestine | K39: 312250
J40: Paraguay | K40: 586400
... J60: Grand Total | K60: 9196000

Sheet kiva_loans (muestra)
A1: id | B1: funded_amount | C1: loan_amount | D1: activity | E1: sector | F1: use | G1: country_code | H1: country | I1: region | J1: currency | K1: partner_id | L1: posted_time | M1: disbursed_time | N1: funded_time | O1: term_in_months | P1: lender_count | Q1: borrower_genders | R1: repayment_interval | S1: date | T1: Nivel de Credito | U1: Continente | V1: Icono
A2: 654167 | B2: 2450 | C2: 2450 | D2: Livestock | E2: Agriculture | F2: to buy a dairy cow | G2: AL | H2: Albania | I2: Korce | J2: ALL | K2: 2390 | L2: 41645.479 | M2: 41631.333 | N2: 41653.64 | O2: 38 | P2: 94 | Q2: female | R2: monthly | S2: 41645 | T2: =IF(kiva_loans__muestra[[#This Row],[loan_amount]]>5000,"Alto","Bajo") -> Bajo | U2: =VLOOKUP(kiva_loans__muestra[[#This Row],[country]],Pais!A:B,2,FALSE) -> Rest of Europe | V2: 👩 F
A3: 655765 | B3: 2425 | C3: 2425 | D3: Dairy | E3: Agriculture | F3: to buy a dairy cow | G3: AL | H3: Albania | I3: Elbasan | J3: ALL | K3: 2390 | L3: 41648.565 | M3: 41621.333 | N3: 41659.048 | O3: 32 | P3: 93 | Q3: male | R3: monthly | S3: 41648 | T3: =IF(kiva_loans__muestra[[#This Row],[loan_amount]]>5000,"Alto","Bajo") -> Bajo | U3: =VLOOKUP(kiva_loans__muestra[[#This Row],[country]],Pais!A:B,2,FALSE) -> Rest of Europe | V3: 👨‍🦰M
A4: 655779 | B4: 975 | C4: 975 | D4: Livestock | E4: Agriculture | F4: to buy fodder for her animals | G4: AL | H4: Albania | I4: Korce | J4: ALL | K4: 2390 | L4: 41648.603 | M4: 41638.333 | N4: 41652.081 | O4: 21 | P4: 26 | Q4: female | R4: monthly | S4: 41648 | T4: =IF(kiva_loans__muestra[[#This Row],[loan_amount]]>5000,"Alto","Bajo") -> Bajo | U4: =VLOOKUP(kiva_loans__muestra[[#This Row],[country]],Pais!A:B,2,FALSE) -> Rest of Europe | V4: 👩 F
A5: 656172 | B5: 975 | C5: 975 | D5: Livestock | E5: Agriculture | F5: to buy baby goats. | G5: AL | H5: Albania | I5: Elbasan | J5: ALL | K5: 2390 | L5: 41649.595 | M5: 41649.333 | N5: 41650.915 | O5: 20 | P5: 37 | Q5: male | R5: monthly | S5: 41649 | T5: =IF(kiva_loans__muestra[[#This Row],[loan_amount]]>5000,"Alto","Bajo") -> Bajo | U5: =VLOOKUP(kiva_loans__muestra[[#This Row],[country]],Pais!A:B,2,FALSE) -> Rest of Europe | V5: 👨‍🦰M
A6: 656175 | B6: 975 | C6: 975 | D6: Grocery Store | E6: Food | F6: To stock up on inventory items for her grocery store and also buy fodder for the animals | G6: AL | H6: Albania | J6: ALL | K6: 2390 | L6: 41649.605 | M6: 41648.333 | N6: 41652.926 | O6: 20 | P6: 31 | Q6: female | R6: monthly | S6: 41649 | T6: =IF(kiva_loans__muestra[[#This Row],[loan_amount]]>5000,"Alto","Bajo") -> Bajo | U6: =VLOOKUP(kiva_loans__muestra[[#This Row],[country]],Pais!A:B,2,FALSE) -> Rest of Europe | V6: 👩 F
A7: 656708 | B7: 1950 | C7: 1950 | D7: Used Clothing | E7: Clothing | F7: To buy used clothes to resell | G7: AL | H7: Albania | J7: ALL | K7: 2390 | L7: 41652.586 | M7: 41649.333 | N7: 41659.548 | O7: 26 | P7: 70 | Q7: male | R7: monthly | S7: 41652 | T7: =IF(kiva_loans__muestra[[#This Row],[loan_amount]]>5000,"Alto","Bajo") -> Bajo | U7: =VLOOKUP(kiva_loans__muestra[[#This Row],[country]],Pais!A:B,2,FALSE) -> Rest of Europe | V7: 👨‍🦰M
A8: 656716 | B8: 975 | C8: 975 | D8: Personal Housing Expenses | E8: Housing | F8: to repair the family house. | G8: AL | H8: Albania | I8: Elbasan | J8: ALL | K8: 2390 | L8: 41652.605 | M8: 41649.333 | N8: 41658.459 | O8: 20 | P8: 39 | Q8: female | R8: monthly | S8: 41652 | T8: =IF(kiva_loans__muestra[[#This Row],[loan_amount]]>5000,"Alto","Bajo") -> Bajo | U8: =VLOOKUP(kiva_loans__muestra[[#This Row],[country]],Pais!A:B,2,FALSE) -> Rest of Europe | V8: 👩 F
A9: 656724 | B9: 775 | C9: 775 | D9: Used Clothing | E9: Clothing | F9: to buy second-hand clothing to resell and to repair a damaged balcony of the family home | G9: AL | H9: Albania | I9: Korce | J9: ALL | K9: 2390 | L9: 41652.629 | M9: 41652.333 | N9: 41653.732 | O9: 17 | P9: 27 | Q9: male | R9: monthly | S9: 41652 | T9: =IF(kiva_loans__muestra[[#This Row],[loan_amount]]>5000,"Alto","Bajo") -> Bajo | U9: =VLOOKUP(kiva_loans__muestra[[#This Row],[country]],Pais!A:B,2,FALSE) -> Rest of Europe | V9: 👨‍🦰M
A10: 656731 | B10: 1950 | C10: 1950 | D10: Livestock | E10: Agriculture | F10: to buy a dairy cow | G10: AL | H10: Albania | I10: Lezhe | J10: ALL | K10: 2390 | L10: 41652.641 | M10: 41647.333 | N10: 41658.637 | O10: 29 | P10: 62 | Q10: female | R10: monthly | S10: 41652 | T10: =IF(kiva_loans__muestra[[#This Row],[loan_amount]]>5000,"Alto","Bajo") -> Bajo | U10: =VLOOKUP(kiva_loans__muestra[[#This Row],[country]],Pais!A:B,2,FALSE) -> Rest of Europe | V10: 👩 F
A11: 657018 | B11: 1475 | C11: 1475 | D11: Personal Housing Expenses | E11: Housing | F11: to buy a cheap bed and other furniture as they cannot handle sleeping on the cold floors any longer | G11: AL | H11: Albania | I11: Korce | J11: ALL | K11: 2390 | L11: 41653.401 | M11: 41652.333 | N11: 41653.846 | O11: 14 | P11: 35 | Q11: female | R11: monthly | S11: 41653 | T11: =IF(kiva_loans__muestra[[#This Row],[loan_amount]]>5000,"Alto","Bajo") -> Bajo | U11: =VLOOKUP(kiva_loans__muestra[[#This Row],[country]],Pais!A:B,2,FALSE) -> Rest of Europe | V11: 👩 F
A12: 657977 | B12: 975 | C12: 975 | D12: Higher education costs | E12: Education | F12: To pay her son's last college tuition fees. | G12: AL | H12: Albania | J12: ALL | K12: 2390 | L12: 41655.427 | M12: 41654.333 | N12: 41656.574 | O12: 14 | P12: 37 | Q12: female | R12: monthly | S12: 41655 | T12: =IF(kiva_loans__muestra[[#This Row],[loan_amount]]>5000,"Alto","Bajo") -> Bajo | U12: =VLOOKUP(kiva_loans__muestra[[#This Row],[country]],Pais!A:B,2,FALSE) -> Rest of Europe | V12: 👩 F
A13: 658089 | B13: 975 | C13: 975 | D13: Personal Housing Expenses | E13: Housing | F13: to repair his family home. | G13: AL | H13: Albania | J13: ALL | K13: 2390 | L13: 41655.609 | M13: 41654.333 | N13: 41658.624 | O13: 20 | P13: 39 | Q13: male | R13: monthly | S13: 41655 | T13: =IF(kiva_loans__muestra[[#This Row],[loan_amount]]>5000,"Alto","Bajo") -> Bajo | U13: =VLOOKUP(kiva_loans__muestra[[#This Row],[country]],Pais!A:B,2,FALSE) -> Rest of Europe | V13: 👨‍🦰M
A14: 658562 | B14: 1475 | C14: 1475 | D14: Personal Housing Expenses | E14: Housing | F14: to finish the roofing of one room | G14: AL | H14: Albania | J14: ALL | K14: 2390 | L14: 41656.459 | M14: 41655.333 | N14: 41668.758 | O14: 20 | P14: 49 | Q14: female | R14: monthly | S14: 41656 | T14: =IF(kiva_loans__muestra[[#This Row],[loan_amount]]>5000,"Alto","Bajo") -> Bajo | U14: =VLOOKUP(kiva_loans__muestra[[#This Row],[country]],Pais!A:B,2,FALSE) -> Rest of Europe | V14: 👩 F
A15: 658570 | B15: 1950 | C15: 1950 | D15: Personal Housing Expenses | E15: Housing | F15: to do some work on the family home; the little kids have been feeling very cold this winter | G15: AL | H15: Albania | I15: Korce | J15: ALL | K15: 2390 | L15: 41656.471 | M15: 41655.333 | N15: 41659.74 | O15: 22 | P15: 71 | Q15: female | R15: monthly | S15: 41656 | T15: =IF(kiva_loans__muestra[[#This Row],[loan_amount]]>5000,"Alto","Bajo") -> Bajo | U15: =VLOOKUP(kiva_loans__muestra[[#This Row],[country]],Pais!A:B,2,FALSE) -> Rest of Europe | V15: 👩 F
A16: 659454 | B16: 975 | C16: 975 | D16: Services | E16: Services | F16: to buy equipment for his plumbing services | G16: AL | H16: Albania | I16: Korce | J16: ALL | K16: 2390 | L16: 41659.603 | M16: 41656.333 | N16: 41661.803 | O16: 20 | P16: 36 | Q16: male | R16: monthly | S16: 41659 | T16: =IF(kiva_loans__muestra[[#This Row],[loan_amount]]>5000,"Alto","Bajo") -> Bajo | U16: =VLOOKUP(kiva_loans__muestra[[#This Row],[country]],Pais!A:B,2,FALSE) -> Rest of Europe | V16: 👨‍🦰M
A17: 659457 | B17: 1450 | C17: 1450 | D17: Upholstery | E17: Services | F17: to buy fabric for custom drapery services | G17: AL | H17: Albania | I17: Korce | J17: ALL | K17: 2390 | L17: 41659.617 | M17: 41656.333 | N17: 41665.056 | O17: 14 | P17: 53 | Q17: female | R17: monthly | S17: 41659 | T17: =IF(kiva_loans__muestra[[#This Row],[loan_amount]]>5000,"Alto","Bajo") -> Bajo | U17: =VLOOKUP(kiva_loans__muestra[[#This Row],[country]],Pais!A:B,2,FALSE) -> Rest of Europe | V17: 👩 F
A18: 659840 | B18: 675 | C18: 675 | D18: Dairy | E18: Agriculture | F18: to buy a dairy cow | G18: AL | H18: Albania | I18: Lezhe | J18: ALL | K18: 2390 | L18: 41660.383 | M18: 41656.333 | N18: 41661.168 | O18: 14 | P18: 24 | Q18: female | R18: monthly | S18: 41660 | T18: =IF(kiva_loans__muestra[[#This Row],[loan_amount]]>5000,"Alto","Bajo") -> Bajo | U18: =VLOOKUP(kiva_loans__muestra[[#This Row],[country]],Pais!A:B,2,FALSE) -> Rest of Europe | V18: 👩 F
A19: 659926 | B19: 1950 | C19: 1950 | D19: Agriculture | E19: Agriculture | F19: to repair a leaking roof. | G19: AL | H19: Albania | I19: Lezhe | J19: ALL | K19: 2390 | L19: 41660.492 | M19: 41659.333 | N19: 41661.81 | O19: 27 | P19: 69 | Q19: female | R19: monthly | S19: 41660 | T19: =IF(kiva_loans__muestra[[#This Row],[loan_amount]]>5000,"Alto","Bajo") -> Bajo | U19: =VLOOKUP(kiva_loans__muestra[[#This Row],[country]],Pais!A:B,2,FALSE) -> Rest of Europe | V19: 👩 F
A20: 659934 | B20: 600 | C20: 600 | D20: Agriculture | E20: Agriculture | F20: to buy onion seeds to plant. | G20: AL | H20: Albania | I20: Korce | J20: ALL | K20: 2390 | L20: 41660.505 | M20: 41656.333 | N20: 41661.19 | O20: 13 | P20: 20 | Q20: female | R20: monthly | S20: 41660 | T20: =IF(kiva_loans__muestra[[#This Row],[loan_amount]]>5000,"Alto","Bajo") -> Bajo | U20: =VLOOKUP(kiva_loans__muestra[[#This Row],[country]],Pais!A:B,2,FALSE) -> Rest of Europe | V20: 👩 F
A21: 659972 | B21: 975 | C21: 975 | D21: Agriculture | E21: Agriculture | F21: to buy a water pump for watering the plants | G21: AL | H21: Albania | I21: Korce | J21: ALL | K21: 2390 | L21: 41660.559 | M21: 41659.333 | N21: 41662.767 | O21: 26 | P21: 34 | Q21: male | R21: monthly | S21: 41660 | T21: =IF(kiva_loans__muestra[[#This Row],[loan_amount]]>5000,"Alto","Bajo") -> Bajo | U21: =VLOOKUP(kiva_loans__muestra[[#This Row],[country]],Pais!A:B,2,FALSE) -> Rest of Europe | V21: 👨‍🦰M
A22: 659980 | B22: 775 | C22: 775 | D22: Agriculture | E22: Agriculture | F22: to pay for the agricultural land certification registration documents | G22: AL | H22: Albania | I22: Elbasan | J22: ALL | K22: 2390 | L22: 41660.568 | M22: 41656.333 | N22: 41662.74 | O22: 14 | P22: 28 | Q22: female | R22: monthly | S22: 41660 | T22: =IF(kiva_loans__muestra[[#This Row],[loan_amount]]>5000,"Alto","Bajo") -> Bajo | U22: =VLOOKUP(kiva_loans__muestra[[#This Row],[country]],Pais!A:B,2,FALSE) -> Rest of Europe | V22: 👩 F
A23: 659986 | B23: 2425 | C23: 2425 | D23: Dairy | E23: Agriculture | F23: to buy baby calves | G23: AL | H23: Albania | I23: Korce | J23: ALL | K23: 2390 | L23: 41660.577 | M23: 41660.333 | N23: 41669.025 | O23: 24 | P23: 78 | Q23: female | R23: monthly | S23: 41660 | T23: =IF(kiva_loans__muestra[[#This Row],[loan_amount]]>5000,"Alto","Bajo") -> Bajo | U23: =VLOOKUP(kiva_loans__muestra[[#This Row],[country]],Pais!A:B,2,FALSE) -> Rest of Europe | V23: 👩 F
A24: 659989 | B24: 500 | C24: 500 | D24: Construction | E24: Construction | F24: To buy construction tools for her husband who does construction work | G24: AL | H24: Albania | J24: ALL | K24: 2390 | L24: 41660.583 | M24: 41660.333 | N24: 41661.728 | O24: 14 | P24: 19 | Q24: female | R24: monthly | S24: 41660 | T24: =IF(kiva_loans__muestra[[#This Row],[loan_amount]]>5000,"Alto","Bajo") -> Bajo | U24: =VLOOKUP(kiva_loans__muestra[[#This Row],[country]],Pais!A:B,2,FALSE) -> Rest of Europe | V24: 👩 F
A25: 660454 | B25: 2425 | C25: 2425 | D25: Personal Medical Expenses | E25: Health | F25: to pay for an urgent eye operation for her husband before he goes completely blind. | G25: AL | H25: Albania | I25: Korce | J25: ALL | K25: 2390 | L25: 41661.493 | M25: 41659.333 | N25: 41661.977 | O25: 38 | P25: 77 | Q25: female | R25: monthly | S25: 41661 | T25: =IF(kiva_loans__muestra[[#This Row],[loan_amount]]>5000,"Alto","Bajo") -> Bajo | U25: =VLOOKUP(kiva_loans__muestra[[#This Row],[country]],Pais!A:B,2,FALSE) -> Rest of Europe | V25: 👩 F
A26: 660997 | B26: 2425 | C26: 2425 | D26: Agriculture | E26: Agriculture | F26: to buy red onion seeds for planting | G26: AL | H26: Albania | I26: Korce | J26: ALL | K26: 2390 | L26: 41662.514 | M26: 41661.333 | N26: 41690.548 | O26: 38 | P26: 92 | Q26: female | R26: monthly | S26: 41662 | T26: =IF(kiva_loans__muestra[[#This Row],[loan_amount]]>5000,"Alto","Bajo") -> Bajo | U26: =VLOOKUP(kiva_loans__muestra[[#This Row],[country]],Pais!A:B,2,FALSE) -> Rest of Europe | V26: 👩 F
A27: 661012 | B27: 2425 | C27: 2425 | D27: Higher education costs | E27: Education | F27: to pay for his sons' university tuition fees. | G27: AL | H27: Albania | I27: Korce | J27: ALL | K27: 2390 | L27: 41662.549 | M27: 41660.333 | N27: 41668.66 | O27: 33 | P27: 70 | Q27: male | R27: monthly | S27: 41662 | T27: =IF(kiva_loans__muestra[[#This Row],[loan_amount]]>5000,"Alto","Bajo") -> Bajo | U27: =VLOOKUP(kiva_loans__muestra[[#This Row],[country]],Pais!A:B,2,FALSE) -> Rest of Europe | V27: 👨‍🦰M
A28: 661024 | B28: 500 | C28: 500 | D28: Livestock | E28: Agriculture | F28: to add sheep to her herd of dairy cows | G28: AL | H28: Albania | I28: Korce | J28: ALL | K28: 2390 | L28: 41662.568 | M28: 41659.333 | N28: 41663.631 | O28: 13 | P28: 18 | Q28: female | R28: monthly | S28: 41662 | T28: =IF(kiva_loans__muestra[[#This Row],[loan_amount]]>5000,"Alto","Bajo") -> Bajo | U28: =VLOOKUP(kiva_loans__muestra[[#This Row],[country]],Pais!A:B,2,FALSE) -> Rest of Europe | V28: 👩 F
A29: 661032 | B29: 975 | C29: 975 | D29: Used Clothing | E29: Clothing | G29: AL | H29: Albania | J29: ALL | K29: 2390 | L29: 41662.578 | M29: 41656.333 | N29: 41665.521 | O29: 14 | P29: 36 | Q29: male | R29: monthly | S29: 41662 | T29: =IF(kiva_loans__muestra[[#This Row],[loan_amount]]>5000,"Alto","Bajo") -> Bajo | U29: =VLOOKUP(kiva_loans__muestra[[#This Row],[country]],Pais!A:B,2,FALSE) -> Rest of Europe | V29: 👨‍🦰M
A30: 661354 | B30: 1950 | C30: 1950 | D30: Clothing Sales | E30: Clothing | F30: to stock up on clothing inventory. | G30: AL | H30: Albania | I30: Elbasan | J30: ALL | K30: 2390 | L30: 41663.351 | M30: 41656.333 | N30: 41677.12 | O30: 26 | P30: 69 | Q30: male | R30: monthly | S30: 41663 | T30: =IF(kiva_loans__muestra[[#This Row],[loan_amount]]>5000,"Alto","Bajo") -> Bajo | U30: =VLOOKUP(kiva_loans__muestra[[#This Row],[country]],Pais!A:B,2,FALSE) -> Rest of Europe | V30: 👨‍🦰M
A31: 661360 | B31: 1950 | C31: 1950 | D31: Used Clothing | E31: Clothing | F31: to buy used clothes, shoes and electrical home appliances to sell. | G31: AL | H31: Albania | J31: ALL | K31: 2390 | L31: 41663.358 | M31: 41656.333 | N31: 41668.679 | O31: 26 | P31: 68 | Q31: female | R31: monthly | S31: 41663 | T31: =IF(kiva_loans__muestra[[#This Row],[loan_amount]]>5000,"Alto","Bajo") -> Bajo | U31: =VLOOKUP(kiva_loans__muestra[[#This Row],[country]],Pais!A:B,2,FALSE) -> Rest of Europe | V31: 👩 F
A32: 661387 | B32: 1950 | C32: 1950 | D32: Agriculture | E32: Agriculture | F32: to buy baby goats and sheep. | G32: AL | H32: Albania | I32: Elbasan | J32: ALL | K32: 2390 | L32: 41663.385 | M32: 41659.333 | N32: 41680.764 | O32: 26 | P32: 73 | Q32: male | R32: monthly | S32: 41663 | T32: =IF(kiva_loans__muestra[[#This Row],[loan_amount]]>5000,"Alto","Bajo") -> Bajo | U32: =VLOOKUP(kiva_loans__muestra[[#This Row],[country]],Pais!A:B,2,FALSE) -> Rest of Europe | V32: 👨‍🦰M
A33: 661404 | B33: 1475 | C33: 1475 | D33: Taxi | E33: Transportation | F33: to purchase a taxi vehicle for her husband. | G33: AL | H33: Albania | I33: Elbasan | J33: ALL | K33: 2390 | L33: 41663.401 | M33: 41656.333 | N33: 41672.9 | O33: 20 | P33: 52 | Q33: female | R33: monthly | S33: 41663 | T33: =IF(kiva_loans__muestra[[#This Row],[loan_amount]]>5000,"Alto","Bajo") -> Bajo | U33: =VLOOKUP(kiva_loans__muestra[[#This Row],[country]],Pais!A:B,2,FALSE) -> Rest of Europe | V33: 👩 F
A34: 661415 | B34: 975 | C34: 975 | D34: Agriculture | E34: Agriculture | F34: to buy a dairy cow. | G34: AL | H34: Albania | I34: Elbasan | J34: ALL | K34: 2390 | L34: 41663.412 | M34: 41661.333 | N34: 41664.638 | O34: 20 | P34: 33 | Q34: female | R34: monthly | S34: 41663 | T34: =IF(kiva_loans__muestra[[#This Row],[loan_amount]]>5000,"Alto","Bajo") -> Bajo | U34: =VLOOKUP(kiva_loans__muestra[[#This Row],[country]],Pais!A:B,2,FALSE) -> Rest of Europe | V34: 👩 F
A35: 661438 | B35: 975 | C35: 975 | D35: Farming | E35: Agriculture | F35: to buy potato seeds | G35: AL | H35: Albania | I35: Korce | J35: ALL | K35: 2390 | L35: 41663.446 | M35: 41661.333 | N35: 41665.918 | O35: 10 | P35: 35 | Q35: male | R35: bullet | S35: 41663 | T35: =IF(kiva_loans__muestra[[#This Row],[loan_amount]]>5000,"Alto","Bajo") -> Bajo | U35: =VLOOKUP(kiva_loans__muestra[[#This Row],[country]],Pais!A:B,2,FALSE) -> Rest of Europe | V35: 👨‍🦰M
A36: 661442 | B36: 975 | C36: 975 | D36: Agriculture | E36: Agriculture | F36: to buy onion seeds | G36: AL | H36: Albania | I36: Korce | J36: ALL | K36: 2390 | L36: 41663.455 | M36: 41660.333 | N36: 41664.656 | O36: 20 | P36: 37 | Q36: female | R36: monthly | S36: 41663 | T36: =IF(kiva_loans__muestra[[#This Row],[loan_amount]]>5000,"Alto","Bajo") -> Bajo | U36: =VLOOKUP(kiva_loans__muestra[[#This Row],[country]],Pais!A:B,2,FALSE) -> Rest of Europe | V36: 👩 F
A37: 661458 | B37: 1475 | C37: 1475 | D37: Dairy | E37: Agriculture | F37: add more cows to her existing herd. | G37: AL | H37: Albania | J37: ALL | K37: 2390 | L37: 41663.478 | M37: 41663.333 | N37: 41667.111 | O37: 26 | P37: 51 | Q37: female | R37: monthly | S37: 41663 | T37: =IF(kiva_loans__muestra[[#This Row],[loan_amount]]>5000,"Alto","Bajo") -> Bajo | U37: =VLOOKUP(kiva_loans__muestra[[#This Row],[country]],Pais!A:B,2,FALSE) -> Rest of Europe | V37: 👩 F
A38: 661543 | B38: 1475 | C38: 1475 | D38: Construction | E38: Construction | F38: to do some work at his newly built home that he will use for business as well | G38: AL | H38: Albania | I38: Elbasan | J38: ALL | K38: 2390 | L38: 41663.586 | M38: 41656.333 | N38: 41688.971 | O38: 20 | P38: 53 | Q38: female | R38: monthly | S38: 41663 | T38: =IF(kiva_loans__muestra[[#This Row],[loan_amount]]>5000,"Alto","Bajo") -> Bajo | U38: =VLOOKUP(kiva_loans__muestra[[#This Row],[country]],Pais!A:B,2,FALSE) -> Rest of Europe | V38: 👩 F
A39: 661544 | B39: 975 | C39: 975 | D39: Hardware | E39: Retail | F39: To stock up on construction materials for his hardware store | G39: AL | H39: Albania | J39: ALL | K39: 2390 | L39: 41663.589 | M39: 41663.333 | N39: 41672.725 | O39: 14 | P39: 33 | Q39: female | R39: monthly | S39: 41663 | T39: =IF(kiva_loans__muestra[[#This Row],[loan_amount]]>5000,"Alto","Bajo") -> Bajo | U39: =VLOOKUP(kiva_loans__muestra[[#This Row],[country]],Pais!A:B,2,FALSE) -> Rest of Europe | V39: 👩 F
A40: 661547 | B40: 500 | C40: 500 | D40: Farming | E40: Agriculture | F40: To buy seeds (potato and onion) for seasonal planting | G40: AL | H40: Albania | J40: ALL | K40: 2390 | L40: 41663.593 | M40: 41662.333 | N40: 41664.947 | O40: 13 | P40: 16 | Q40: male | R40: monthly | S40: 41663 | T40: =IF(kiva_loans__muestra[[#This Row],[loan_amount]]>5000,"Alto","Bajo") -> Bajo | U40: =VLOOKUP(kiva_loans__muestra[[#This Row],[country]],Pais!A:B,2,FALSE) -> Rest of Europe | V40: 👨‍🦰M
A41: 661564 | B41: 1950 | C41: 1950 | D41: Farming | E41: Agriculture | F41: to buy peach seedlings and water pipes | G41: AL | H41: Albania | I41: Elbasan | J41: ALL | K41: 2390 | L41: 41663.618 | M41: 41663.333 | N41: 41669.164 | O41: 38 | P41: 66 | Q41: male | R41: monthly | S41: 41663 | T41: =IF(kiva_loans__muestra[[#This Row],[loan_amount]]>5000,"Alto","Bajo") -> Bajo | U41: =VLOOKUP(kiva_loans__muestra[[#This Row],[country]],Pais!A:B,2,FALSE) -> Rest of Europe | V41: 👨‍🦰M
A42: 662178 | B42: 1950 | C42: 1950 | D42: Farming | E42: Agriculture | F42: to invest in a tractor | G42: AL | H42: Albania | I42: Korce | J42: ALL | K42: 2390 | L42: 41666.371 | M42: 41663.333 | N42: 41673.573 | O42: 20 | P42: 75 | Q42: female | R42: monthly | S42: 41666 | T42: =IF(kiva_loans__muestra[[#This Row],[loan_amount]]>5000,"Alto","Bajo") -> Bajo | U42: =VLOOKUP(kiva_loans__muestra[[#This Row],[country]],Pais!A:B,2,FALSE) -> Rest of Europe | V42: 👩 F
A43: 662185 | B43: 975 | C43: 975 | D43: Agriculture | E43: Agriculture | F43: to buy onion seeds for planting | G43: AL | H43: Albania | I43: Korce | J43: ALL | K43: 2390 | L43: 41666.386 | M43: 41662.333 | N43: 41668.429 | O43: 15 | P43: 38 | Q43: male | R43: monthly | S43: 41666 | T43: =IF(kiva_loans__muestra[[#This Row],[loan_amount]]>5000,"Alto","Bajo") -> Bajo | U43: =VLOOKUP(kiva_loans__muestra[[#This Row],[country]],Pais!A:B,2,FALSE) -> Rest of Europe | V43: 👨‍🦰M
A44: 662214 | B44: 975 | C44: 975 | D44: Farming | E44: Agriculture | F44: to buy water pipes for the irrigation of the planted field | G44: AL | H44: Albania | I44: Elbasan | J44: ALL | K44: 2390 | L44: 41666.415 | M44: 41663.333 | N44: 41667.454 | O44: 17 | P44: 10 | Q44: female | R44: monthly | S44: 41666 | T44: =IF(kiva_loans__muestra[[#This Row],[loan_amount]]>5000,"Alto","Bajo") -> Bajo | U44: =VLOOKUP(kiva_loans__muestra[[#This Row],[country]],Pais!A:B,2,FALSE) -> Rest of Europe | V44: 👩 F
A45: 662240 | B45: 1475 | C45: 1475 | D45: Cafe | E45: Food | F45: to buy equipment for her bar-cafe. | G45: AL | H45: Albania | I45: Elbasan | J45: ALL | K45: 2390 | L45: 41666.435 | M45: 41663.333 | N45: 41668.709 | O45: 26 | P45: 55 | Q45: male | R45: monthly | S45: 41666 | T45: =IF(kiva_loans__muestra[[#This Row],[loan_amount]]>5000,"Alto","Bajo") -> Bajo | U45: =VLOOKUP(kiva_loans__muestra[[#This Row],[country]],Pais!A:B,2,FALSE) -> Rest of Europe | V45: 👨‍🦰M
A46: 662385 | B46: 1475 | C46: 1475 | D46: Personal Housing Expenses | E46: Housing | F46: to install doors and windows in his family home shown in the background of the picture. | G46: AL | H46: Albania | I46: Lezhe | J46: ALL | K46: 2390 | L46: 41666.583 | M46: 41663.333 | N46: 41672.909 | O46: 26 | P46: 32 | Q46: male | R46: monthly | S46: 41666 | T46: =IF(kiva_loans__muestra[[#This Row],[loan_amount]]>5000,"Alto","Bajo") -> Bajo | U46: =VLOOKUP(kiva_loans__muestra[[#This Row],[country]],Pais!A:B,2,FALSE) -> Rest of Europe | V46: 👨‍🦰M
A47: 662388 | B47: 975 | C47: 975 | D47: Personal Housing Expenses | E47: Housing | F47: To replace the windows and front door in her home | G47: AL | H47: Albania | J47: ALL | K47: 2390 | L47: 41666.59 | M47: 41666.333 | N47: 41668.671 | O47: 21 | P47: 35 | Q47: male | R47: monthly | S47: 41666 | T47: =IF(kiva_loans__muestra[[#This Row],[loan_amount]]>5000,"Alto","Bajo") -> Bajo | U47: =VLOOKUP(kiva_loans__muestra[[#This Row],[country]],Pais!A:B,2,FALSE) -> Rest of Europe | V47: 👨‍🦰M
A48: 662398 | B48: 975 | C48: 975 | D48: Personal Medical Expenses | E48: Health | F48: to cover her mother's surgery. | G48: AL | H48: Albania | I48: Korce | J48: ALL | K48: 2390 | L48: 41666.607 | M48: 41661.333 | N48: 41667.313 | O48: 15 | P48: 35 | Q48: male | R48: monthly | S48: 41666 | T48: =IF(kiva_loans__muestra[[#This Row],[loan_amount]]>5000,"Alto","Bajo") -> Bajo | U48: =VLOOKUP(kiva_loans__muestra[[#This Row],[country]],Pais!A:B,2,FALSE) -> Rest of Europe | V48: 👨‍🦰M
A49: 655547 | B49: 625 | C49: 625 | D49: Taxi | E49: Transportation | F49: to pay for winter tires and repair the vehicle | G49: AM | H49: Armenia | I49: Vanadzor town | J49: AMD | K49: 1690 | L49: 41648.297 | M49: 41619.333 | N49: 41666.761 | O49: 27 | P49: 19 | Q49: male | R49: monthly | S49: 41648 | T49: =IF(kiva_loans__muestra[[#This Row],[loan_amount]]>5000,"Alto","Bajo") -> Bajo | U49: =VLOOKUP(kiva_loans__muestra[[#This Row],[country]],Pais!A:B,2,FALSE) -> Rest of Europe | V49: 👨‍🦰M
A50: 655560 | B50: 1125 | C50: 1125 | D50: Construction | E50: Construction | F50: to pay for a car | G50: AM | H50: Armenia | I50: Vanadzor town | J50: AMD | K50: 1690 | L50: 41648.313 | M50: 41619.333 | N50: 41678.643 | O50: 26 | P50: 26 | Q50: female | R50: monthly | S50: 41648 | T50: =IF(kiva_loans__muestra[[#This Row],[loan_amount]]>5000,"Alto","Bajo") -> Bajo | U50: =VLOOKUP(kiva_loans__muestra[[#This Row],[country]],Pais!A:B,2,FALSE) -> Rest of Europe | V50: 👩 F
A51: 655566 | B51: 1000 | C51: 1000 | D51: Cafe | E51: Food | F51: to pay for food products for her cafe | G51: AM | H51: Armenia | I51: Yerevan | J51: AMD | K51: 1690 | L51: 41648.324 | M51: 41635.333 | N51: 41661.696 | O51: 27 | P51: 36 | Q51: female | R51: monthly | S51: 41648 | T51: =IF(kiva_loans__muestra[[#This Row],[loan_amount]]>5000,"Alto","Bajo") -> Bajo | U51: =VLOOKUP(kiva_loans__muestra[[#This Row],[country]],Pais!A:B,2,FALSE) -> Rest of Europe | V51: 👩 F
A52: 655571 | B52: 750 | C52: 750 | D52: Bakery | E52: Food | F52: to pay for materials and tools needed for her bakery | G52: AM | H52: Armenia | I52: Yerevan | J52: AMD | K52: 1690 | L52: 41648.328 | M52: 41634.333 | N52: 41653.834 | O52: 27 | P52: 24 | Q52: female | R52: monthly | S52: 41648 | T52: =IF(kiva_loans__muestra[[#This Row],[loan_amount]]>5000,"Alto","Bajo") -> Bajo | U52: =VLOOKUP(kiva_loans__muestra[[#This Row],[country]],Pais!A:B,2,FALSE) -> Rest of Europe | V52: 👩 F
A53: 655590 | B53: 150 | C53: 1500 | D53: Transportation | E53: Transportation | F53: to pay for renovation of the truck and purchase fruits for resale | G53: AM | H53: Armenia | I53: Shnogh village | J53: AMD | K53: 1690 | L53: 41648.347 | M53: 41632.333 | O53: 27 | P53: 6 | Q53: female | R53: monthly | S53: 41648 | T53: =IF(kiva_loans__muestra[[#This Row],[loan_amount]]>5000,"Alto","Bajo") -> Bajo | U53: =VLOOKUP(kiva_loans__muestra[[#This Row],[country]],Pais!A:B,2,FALSE) -> Rest of Europe | V53: 👩 F
A54: 655605 | B54: 1500 | C54: 1500 | D54: Clothing Sales | E54: Clothing | F54: to pay for a new stock of clothing to sell to customers. | G54: AM | H54: Armenia | I54: Vanadzor town | J54: AMD | K54: 1690 | L54: 41648.361 | M54: 41634.333 | N54: 41676.966 | O54: 27 | P54: 57 | Q54: female | R54: monthly | S54: 41648 | T54: =IF(kiva_loans__muestra[[#This Row],[loan_amount]]>5000,"Alto","Bajo") -> Bajo | U54: =VLOOKUP(kiva_loans__muestra[[#This Row],[country]],Pais!A:B,2,FALSE) -> Rest of Europe | V54: 👩 F
A55: 655637 | B55: 1500 | C55: 1500 | D55: Construction | E55: Construction | F55: to buy tools for providing renovation services | G55: AM | H55: Armenia | I55: Kapan, Syunik region | J55: AMD | K55: 1690 | L55: 41648.401 | M55: 41632.333 | N55: 41663.646 | O55: 26 | P55: 43 | Q55: female | R55: monthly | S55: 41648 | T55: =IF(kiva_loans__muestra[[#This Row],[loan_amount]]>5000,"Alto","Bajo") -> Bajo | U55: =VLOOKUP(kiva_loans__muestra[[#This Row],[country]],Pais!A:B,2,FALSE) -> Rest of Europe | V55: 👩 F
A56: 655642 | B56: 1500 | C56: 1500 | D56: Clothing Sales | E56: Clothing | F56: to pay for a new stock of clothing to sell to customers. | G56: AM | H56: Armenia | I56: Kapan, Syunik region | J56: AMD | K56: 1690 | L56: 41648.406 | M56: 41632.333 | N56: 41673.637 | O56: 26 | P56: 48 | Q56: male | R56: monthly | S56: 41648 | T56: =IF(kiva_loans__muestra[[#This Row],[loan_amount]]>5000,"Alto","Bajo") -> Bajo | U56: =VLOOKUP(kiva_loans__muestra[[#This Row],[country]],Pais!A:B,2,FALSE) -> Rest of Europe | V56: 👨‍🦰M
A57: 655658 | B57: 1150 | C57: 1250 | D57: Decorations Sales | E57: Retail | F57: to pay for flowers, baskets and materials to sell flowers | G57: AM | H57: Armenia | I57: Gyumri | J57: AMD | K57: 1690 | L57: 41648.428 | M57: 41635.333 | O57: 27 | P57: 19 | Q57: female | R57: monthly | S57: 41648 | T57: =IF(kiva_loans__muestra[[#This Row],[loan_amount]]>5000,"Alto","Bajo") -> Bajo | U57: =VLOOKUP(kiva_loans__muestra[[#This Row],[country]],Pais!A:B,2,FALSE) -> Rest of Europe | V57: 👩 F
A58: 655666 | B58: 625 | C58: 1250 | D58: Transportation | E58: Transportation | F58: to pay for new tires, renovation of the car and also to purchase a new sewing machine for his sewing business. | G58: AM | H58: Armenia | I58: Gyumri | J58: AMD | K58: 1690 | L58: 41648.435 | M58: 41632.333 | O58: 26 | P58: 20 | Q58: female | R58: monthly | S58: 41648 | T58: =IF(kiva_loans__muestra[[#This Row],[loan_amount]]>5000,"Alto","Bajo") -> Bajo | U58: =VLOOKUP(kiva_loans__muestra[[#This Row],[country]],Pais!A:B,2,FALSE) -> Rest of Europe | V58: 👩 F
A59: 655697 | B59: 300 | C59: 1500 | D59: Taxi | E59: Transportation | F59: to pay for new tires and to renovate his car. | G59: AM | H59: Armenia | I59: Gyumri | J59: AMD | K59: 1690 | L59: 41648.481 | M59: 41618.333 | O59: 26 | P59: 5 | Q59: male | R59: monthly | S59: 41648 | T59: =IF(kiva_loans__muestra[[#This Row],[loan_amount]]>5000,"Alto","Bajo") -> Bajo | U59: =VLOOKUP(kiva_loans__muestra[[#This Row],[country]],Pais!A:B,2,FALSE) -> Rest of Europe | V59: 👨‍🦰M
A60: 655703 | B60: 750 | C60: 750 | D60: Retail | E60: Retail | F60: to pay for new flower seeds and flowers for selling to customers | G60: AM | H60: Armenia | I60: Goris | J60: AMD | K60: 1690 | L60: 41648.49 | M60: 41636.333 | N60: 41656.847 | O60: 27 | P60: 25 | Q60: female | R60: monthly | S60: 41648 | T60: =IF(kiva_loans__muestra[[#This Row],[loan_amount]]>5000,"Alto","Bajo") -> Bajo | U60: =VLOOKUP(kiva_loans__muestra[[#This Row],[country]],Pais!A:B,2,FALSE) -> Rest of Europe | V60: 👩 F
A61: 655724 | B61: 1250 | C61: 1250 | D61: Furniture Making | E61: Manufacturing | F61: to pay for materials for furniture making | G61: AM | H61: Armenia | I61: Goris | J61: AMD | K61: 1690 | L61: 41648.504 | M61: 41635.333 | N61: 41651.194 | O61: 26 | P61: 36 | Q61: female | R61: monthly | S61: 41648 | T61: =IF(kiva_loans__muestra[[#This Row],[loan_amount]]>5000,"Alto","Bajo") -> Bajo | U61: =VLOOKUP(kiva_loans__muestra[[#This Row],[country]],Pais!A:B,2,FALSE) -> Rest of Europe | V61: 👩 F
A62: 655732 | B62: 1500 | C62: 1500 | D62: Beauty Salon | E62: Services | F62: to pay for tools (chair, table, and materials) for providing hairdresser service | G62: AM | H62: Armenia | I62: Shatin village, Vayots Dzor region | J62: AMD | K62: 1690 | L62: 41648.51 | M62: 41634.333 | N62: 41677.689 | O62: 26 | P62: 39 | Q62: female | R62: monthly | S62: 41648 | T62: =IF(kiva_loans__muestra[[#This Row],[loan_amount]]>5000,"Alto","Bajo") -> Bajo | U62: =VLOOKUP(kiva_loans__muestra[[#This Row],[country]],Pais!A:B,2,FALSE) -> Rest of Europe | V62: 👩 F
A63: 655740 | B63: 425 | C63: 1500 | D63: Auto Repair | E63: Services | F63: to pay for equipment to provide auto repair services | G63: AM | H63: Armenia | I63: Yeghegnadzor, Vayots Dzor region | J63: AMD | K63: 1690 | L63: 41648.516 | M63: 41635.333 | O63: 26 | P63: 12 | Q63: male | R63: monthly | S63: 41648 | T63: =IF(kiva_loans__muestra[[#This Row],[loan_amount]]>5000,"Alto","Bajo") -> Bajo | U63: =VLOOKUP(kiva_loans__muestra[[#This Row],[country]],Pais!A:B,2,FALSE) -> Rest of Europe | V63: 👨‍🦰M
A64: 655757 | B64: 1500 | C64: 1500 | D64: Sewing | E64: Services | F64: to purchase materials for sewing | G64: AM | H64: Armenia | I64: Armavir | J64: AMD | K64: 1690 | L64: 41648.544 | M64: 41632.333 | N64: 41657.672 | O64: 27 | P64: 58 | Q64: female | R64: monthly | S64: 41648 | T64: =IF(kiva_loans__muestra[[#This Row],[loan_amount]]>5000,"Alto","Bajo") -> Bajo | U64: =VLOOKUP(kiva_loans__muestra[[#This Row],[country]],Pais!A:B,2,FALSE) -> Rest of Europe | V64: 👩 F
A65: 655770 | B65: 500 | C65: 500 | D65: Higher education costs | E65: Education | F65: to pay for her university tuition. | G65: AM | H65: Armenia | I65: Mayisyan village, Armavir region | J65: AMD | K65: 1690 | L65: 41648.577 | M65: 41618.333 | N65: 41649.447 | O65: 14 | P65: 18 | Q65: female | R65: monthly | S65: 41648 | T65: =IF(kiva_loans__muestra[[#This Row],[loan_amount]]>5000,"Alto","Bajo") -> Bajo | U65: =VLOOKUP(kiva_loans__muestra[[#This Row],[country]],Pais!A:B,2,FALSE) -> Rest of Europe | V65: 👩 F
A66: 656185 | B66: 3000 | C66: 3000 | D66: Agriculture | E66: Agriculture | F66: to pay for forage for feeding the livestock | G66: AM | H66: Armenia | I66: Ashotavan community, Syunik region | J66: USD | K66: 1690 | L66: 41649.636 | M66: 41619.333 | N66: 41669.138 | O66: 26 | P66: 99 | Q66: male | R66: monthly | S66: 41649 | T66: =IF(kiva_loans__muestra[[#This Row],[loan_amount]]>5000,"Alto","Bajo") -> Bajo | U66: =VLOOKUP(kiva_loans__muestra[[#This Row],[country]],Pais!A:B,2,FALSE) -> Rest of Europe | V66: 👨‍🦰M
A67: 656534 | B67: 1500 | C67: 1500 | D67: Livestock | E67: Agriculture | F67: to pay for three calves | G67: AM | H67: Armenia | I67: Qarakert village, Armavir region | J67: USD | K67: 1690 | L67: 41652.328 | M67: 41625.333 | N67: 41668.731 | O67: 26 | P67: 44 | Q67: female | R67: monthly | S67: 41652 | T67: =IF(kiva_loans__muestra[[#This Row],[loan_amount]]>5000,"Alto","Bajo") -> Bajo | U67: =VLOOKUP(kiva_loans__muestra[[#This Row],[country]],Pais!A:B,2,FALSE) -> Rest of Europe | V67: 👩 F
A68: 656538 | B68: 2500 | C68: 2500 | D68: Livestock | E68: Agriculture | F68: to pay for 2 cows, 2 oxen and forage for feeding the livestock. | G68: AM | H68: Armenia | I68: Dalarik village of Armavir region | J68: USD | K68: 1690 | L68: 41652.34 | M68: 41624.333 | N68: 41665.404 | O68: 26 | P68: 60 | Q68: female | R68: monthly | S68: 41652 | T68: =IF(kiva_loans__muestra[[#This Row],[loan_amount]]>5000,"Alto","Bajo") -> Bajo | U68: =VLOOKUP(kiva_loans__muestra[[#This Row],[country]],Pais!A:B,2,FALSE) -> Rest of Europe | V68: 👩 F
A69: 656600 | B69: 3000 | C69: 3000 | D69: Agriculture | E69: Agriculture | F69: to pay for the renovation of the greenhouse as well as for fertilizer and wheat seeds. | G69: AM | H69: Armenia | I69: Margara village, Armavir region | J69: USD | K69: 1690 | L69: 41652.436 | M69: 41628.333 | N69: 41661.721 | O69: 26 | P69: 90 | Q69: female | R69: monthly | S69: 41652 | T69: =IF(kiva_loans__muestra[[#This Row],[loan_amount]]>5000,"Alto","Bajo") -> Bajo | U69: =VLOOKUP(kiva_loans__muestra[[#This Row],[country]],Pais!A:B,2,FALSE) -> Rest of Europe | V69: 👩 F
A70: 656638 | B70: 600 | C70: 600 | D70: Agriculture | E70: Agriculture | F70: to purchase forage for feeding the livestock | G70: AM | H70: Armenia | I70: Shenavan village, Armavir region | J70: USD | K70: 1690 | L70: 41652.485 | M70: 41631.333 | N70: 41657.633 | O70: 14 | P70: 17 | Q70: male | R70: monthly | S70: 41652 | T70: =IF(kiva_loans__muestra[[#This Row],[loan_amount]]>5000,"Alto","Bajo") -> Bajo | U70: =VLOOKUP(kiva_loans__muestra[[#This Row],[country]],Pais!A:B,2,FALSE) -> Rest of Europe | V70: 👨‍🦰M
A71: 656654 | B71: 575 | C71: 1500 | D71: Agriculture | E71: Agriculture | F71: to pay for land. | G71: AM | H71: Armenia | I71: Pshatavan village, Armavir region | J71: USD | K71: 1690 | L71: 41652.501 | M71: 41632.333 | O71: 39 | P71: 18 | Q71: female | R71: monthly | S71: 41652 | T71: =IF(kiva_loans__muestra[[#This Row],[loan_amount]]>5000,"Alto","Bajo") -> Bajo | U71: =VLOOKUP(kiva_loans__muestra[[#This Row],[country]],Pais!A:B,2,FALSE) -> Rest of Europe | V71: 👩 F
A72: 656666 | B72: 1500 | C72: 1500 | D72: Livestock | E72: Agriculture | F72: to pay for a cow, a pig and forage for feeding the livestock. | G72: AM | H72: Armenia | I72: Miasnikyan village of Armavir region | J72: USD | K72: 1690 | L72: 41652.51 | M72: 41632.333 | N72: 41656.958 | O72: 27 | P72: 45 | Q72: female | R72: monthly | S72: 41652 | T72: =IF(kiva_loans__muestra[[#This Row],[loan_amount]]>5000,"Alto","Bajo") -> Bajo | U72: =VLOOKUP(kiva_loans__muestra[[#This Row],[country]],Pais!A:B,2,FALSE) -> Rest of Europe | V72: 👩 F
A73: 656676 | B73: 325 | C73: 325 | D73: Higher education costs | E73: Education | F73: to pay for university tuition. | G73: AM | H73: Armenia | I73: Armavir | J73: AMD | K73: 1690 | L73: 41652.521 | M73: 41633.333 | N73: 41654.424 | O73: 15 | P73: 13 | Q73: female | R73: monthly | S73: 41652 | T73: =IF(kiva_loans__muestra[[#This Row],[loan_amount]]>5000,"Alto","Bajo") -> Bajo | U73: =VLOOKUP(kiva_loans__muestra[[#This Row],[country]],Pais!A:B,2,FALSE) -> Rest of Europe | V73: 👩 F
A74: 656697 | B74: 1000 | C74: 1000 | D74: Agriculture | E74: Agriculture | F74: to pay for 3 pigs, forage for feeding livestock, fertilizer and seeds | G74: AM | H74: Armenia | I74: Dalarik village of Armavir region | J74: USD | K74: 1690 | L74: 41652.56 | M74: 41633.333 | N74: 41662.824 | O74: 27 | P74: 23 | Q74: female | R74: monthly | S74: 41652 | T74: =IF(kiva_loans__muestra[[#This Row],[loan_amount]]>5000,"Alto","Bajo") -> Bajo | U74: =VLOOKUP(kiva_loans__muestra[[#This Row],[country]],Pais!A:B,2,FALSE) -> Rest of Europe | V74: 👩 F
A75: 656700 | B75: 975 | C75: 2500 | D75: Agriculture | E75: Agriculture | F75: to pay for renovation of the greenhouse, an ox, and forage for feeding livestock. | G75: AM | H75: Armenia | I75: Taperakan village, Ararat region | J75: USD | K75: 1690 | L75: 41652.566 | M75: 41625.333 | O75: 26 | P75: 21 | Q75: female | R75: monthly | S75: 41652 | T75: =IF(kiva_loans__muestra[[#This Row],[loan_amount]]>5000,"Alto","Bajo") -> Bajo | U75: =VLOOKUP(kiva_loans__muestra[[#This Row],[country]],Pais!A:B,2,FALSE) -> Rest of Europe | V75: 👩 F
A76: 656704 | B76: 775 | C76: 3000 | D76: Agriculture | E76: Agriculture | F76: to pay for pipe and a plastic cover (for the greenhouse) and purchase forage for feeding the livestock | G76: AM | H76: Armenia | I76: Gay village, Armavir region | J76: USD | K76: 1690 | L76: 41652.575 | M76: 41624.333 | O76: 26 | P76: 26 | Q76: male | R76: monthly | S76: 41652 | T76: =IF(kiva_loans__muestra[[#This Row],[loan_amount]]>5000,"Alto","Bajo") -> Bajo | U76: =VLOOKUP(kiva_loans__muestra[[#This Row],[country]],Pais!A:B,2,FALSE) -> Rest of Europe | V76: 👨‍🦰M
A77: 656707 | B77: 1300 | C77: 1300 | D77: Agriculture | E77: Agriculture | F77: to pay for renovation of the greenhouse | G77: AM | H77: Armenia | I77: Ghukasavan village, Ararat region | J77: USD | K77: 1690 | L77: 41652.583 | M77: 41625.333 | N77: 41656.766 | O77: 38 | P77: 48 | Q77: female | R77: monthly | S77: 41652 | T77: =IF(kiva_loans__muestra[[#This Row],[loan_amount]]>5000,"Alto","Bajo") -> Bajo | U77: =VLOOKUP(kiva_loans__muestra[[#This Row],[country]],Pais!A:B,2,FALSE) -> Rest of Europe | V77: 👩 F
A78: 656964 | B78: 1550 | C78: 3000 | D78: Agriculture | E78: Agriculture | F78: to pay for the renovation of an agricultural machine. | G78: AM | H78: Armenia | I78: Ajarkut village, Tavushi region | J78: USD | K78: 1690 | L78: 41653.319 | M78: 41626.333 | O78: 26 | P78: 31 | Q78: female | R78: monthly | S78: 41653 | T78: =IF(kiva_loans__muestra[[#This Row],[loan_amount]]>5000,"Alto","Bajo") -> Bajo | U78: =VLOOKUP(kiva_loans__muestra[[#This Row],[country]],Pais!A:B,2,FALSE) -> Rest of Europe | V78: 👩 F
A79: 656980 | B79: 550 | C79: 1000 | D79: Agriculture | E79: Agriculture | F79: to pay for two pigs and forage for feeding them. | G79: AM | H79: Armenia | I79: Gandzaqar village, Tavush region | J79: USD | K79: 1690 | L79: 41653.351 | M79: 41626.333 | O79: 26 | P79: 16 | Q79: female | R79: monthly | S79: 41653 | T79: =IF(kiva_loans__muestra[[#This Row],[loan_amount]]>5000,"Alto","Bajo") -> Bajo | U79: =VLOOKUP(kiva_loans__muestra[[#This Row],[country]],Pais!A:B,2,FALSE) -> Rest of Europe | V79: 👩 F
A80: 656984 | B80: 1500 | C80: 1500 | D80: Livestock | E80: Agriculture | F80: to pay for two mother pigs and forage for feeding them. | G80: AM | H80: Armenia | I80: Gandzaqar village, Tavush region | J80: USD | K80: 1690 | L80: 41653.358 | M80: 41627.333 | N80: 41661.574 | O80: 38 | P80: 57 | Q80: female | R80: monthly | S80: 41653 | T80: =IF(kiva_loans__muestra[[#This Row],[loan_amount]]>5000,"Alto","Bajo") -> Bajo | U80: =VLOOKUP(kiva_loans__muestra[[#This Row],[country]],Pais!A:B,2,FALSE) -> Rest of Europe | V80: 👩 F
A81: 657034 | B81: 1500 | C81: 1500 | D81: Services | E81: Services | F81: to pay for supplies for providing rental service for wedding ceremonies | G81: AM | H81: Armenia | I81: Ejmiatsin | J81: USD | K81: 1690 | L81: 41653.425 | M81: 41628.333 | N81: 41661.228 | O81: 26 | P81: 60 | Q81: male | R81: monthly | S81: 41653 | T81: =IF(kiva_loans__muestra[[#This Row],[loan_amount]]>5000,"Alto","Bajo") -> Bajo | U81: =VLOOKUP(kiva_loans__muestra[[#This Row],[country]],Pais!A:B,2,FALSE) -> Rest of Europe | V81: 👨‍🦰M
A82: 657047 | B82: 1000 | C82: 1000 | D82: Farming | E82: Agriculture | F82: to pay for renovation of the greenhouse and enlarge the cultivation of greens | G82: AM | H82: Armenia | I82: Lernamerdz village, Armavir region | J82: USD | K82: 1690 | L82: 41653.45 | M82: 41631.333 | N82: 41656.338 | O82: 26 | P82: 38 | Q82: female | R82: monthly | S82: 41653 | T82: =IF(kiva_loans__muestra[[#This Row],[loan_amount]]>5000,"Alto","Bajo") -> Bajo | U82: =VLOOKUP(kiva_loans__muestra[[#This Row],[country]],Pais!A:B,2,FALSE) -> Rest of Europe | V82: 👩 F
A83: 657050 | B83: 2000 | C83: 2000 | D83: Agriculture | E83: Agriculture | F83: to pay for pigs, oxen, and forage for feeding the livestock | G83: AM | H83: Armenia | I83: Dalarik village of Armavir region | J83: USD | K83: 1690 | L83: 41653.458 | M83: 41633.333 | N83: 41680.535 | O83: 27 | P83: 52 | Q83: female | R83: monthly | S83: 41653 | T83: =IF(kiva_loans__muestra[[#This Row],[loan_amount]]>5000,"Alto","Bajo") -> Bajo | U83: =VLOOKUP(kiva_loans__muestra[[#This Row],[country]],Pais!A:B,2,FALSE) -> Rest of Europe | V83: 👩 F
A84: 657063 | B84: 3000 | C84: 3000 | D84: Food Market | E84: Food | F84: to pay for food products needed to sell in the store | G84: AM | H84: Armenia | I84: Armavir | J84: USD | K84: 1690 | L84: 41653.473 | M84: 41634.333 | N84: 41684.878 | O84: 27 | P84: 72 | Q84: female | R84: monthly | S84: 41653 | T84: =IF(kiva_loans__muestra[[#This Row],[loan_amount]]>5000,"Alto","Bajo") -> Bajo | U84: =VLOOKUP(kiva_loans__muestra[[#This Row],[country]],Pais!A:B,2,FALSE) -> Rest of Europe | V84: 👩 F
A85: 657074 | B85: 3000 | C85: 3000 | D85: Livestock | E85: Agriculture | F85: to purchase two cows and renovate the barn | G85: AM | H85: Armenia | I85: Verishen village | J85: USD | K85: 1690 | L85: 41653.504 | M85: 41627.333 | N85: 41654.095 | O85: 26 | P85: 90 | Q85: female | R85: monthly | S85: 41653 | T85: =IF(kiva_loans__muestra[[#This Row],[loan_amount]]>5000,"Alto","Bajo") -> Bajo | U85: =VLOOKUP(kiva_loans__muestra[[#This Row],[country]],Pais!A:B,2,FALSE) -> Rest of Europe | V85: 👩 F
A86: 657090 | B86: 675 | C86: 1000 | D86: Livestock | E86: Agriculture | F86: to buy five pigs and forage to feed his livestock. | G86: AM | H86: Armenia | I86: Goris | J86: USD | K86: 1690 | L86: 41653.524 | M86: 41634.333 | O86: 38 | P86: 24 | Q86: female | R86: monthly | S86: 41653 | T86: =IF(kiva_loans__muestra[[#This Row],[loan_amount]]>5000,"Alto","Bajo") -> Bajo | U86: =VLOOKUP(kiva_loans__muestra[[#This Row],[country]],Pais!A:B,2,FALSE) -> Rest of Europe | V86: 👩 F
A87: 657126 | B87: 1000 | C87: 1500 | D87: Livestock | E87: Agriculture | F87: to pay for a calf and forage for feeding the livestock | G87: AM | H87: Armenia | I87: Tavshut village | J87: USD | K87: 1690 | L87: 41653.567 | M87: 41633.333 | O87: 27 | P87: 20 | Q87: female | R87: monthly | S87: 41653 | T87: =IF(kiva_loans__muestra[[#This Row],[loan_amount]]>5000,"Alto","Bajo") -> Bajo | U87: =VLOOKUP(kiva_loans__muestra[[#This Row],[country]],Pais!A:B,2,FALSE) -> Rest of Europe | V87: 👩 F
A88: 657137 | B88: 500 | C88: 500 | D88: Farming | E88: Agriculture | F88: to pay for seeds of greens and a polyethylene cover for the greenhouse. | G88: AM | H88: Armenia | I88: Darakert village, Ararat region | J88: USD | K88: 1690 | L88: 41653.579 | M88: 41627.333 | N88: 41657.607 | O88: 26 | P88: 17 | Q88: female | R88: monthly | S88: 41653 | T88: =IF(kiva_loans__muestra[[#This Row],[loan_amount]]>5000,"Alto","Bajo") -> Bajo | U88: =VLOOKUP(kiva_loans__muestra[[#This Row],[country]],Pais!A:B,2,FALSE) -> Rest of Europe | V88: 👩 F
A89: 657143 | B89: 700 | C89: 700 | D89: Agriculture | E89: Agriculture | F89: to pay for fertilizer and polyethylene cover for the greenhouse | G89: AM | H89: Armenia | I89: Yerevan | J89: USD | K89: 1690 | L89: 41653.586 | M89: 41624.333 | N89: 41663.846 | O89: 38 | P89: 22 | Q89: male | R89: monthly | S89: 41653 | T89: =IF(kiva_loans__muestra[[#This Row],[loan_amount]]>5000,"Alto","Bajo") -> Bajo | U89: =VLOOKUP(kiva_loans__muestra[[#This Row],[country]],Pais!A:B,2,FALSE) -> Rest of Europe | V89: 👨‍🦰M
A90: 657531 | B90: 375 | C90: 375 | D90: Higher education costs | E90: Education | F90: to pay for her son's university tuition | G90: AM | H90: Armenia | I90: Yerevan | J90: AMD | K90: 1690 | L90: 41654.541 | M90: 41627.333 | N90: 41655.062 | O90: 15 | P90: 12 | Q90: female | R90: monthly | S90: 41654 | T90: =IF(kiva_loans__muestra[[#This Row],[loan_amount]]>5000,"Alto","Bajo") -> Bajo | U90: =VLOOKUP(kiva_loans__muestra[[#This Row],[country]],Pais!A:B,2,FALSE) -> Rest of Europe | V90: 👩 F
A91: 657541 | B91: 2200 | C91: 3000 | D91: Agriculture | E91: Agriculture | F91: to pay for forage for the livestock and fertilizer | G91: AM | H91: Armenia | I91: Yerevan | J91: USD | K91: 1690 | L91: 41654.575 | M91: 41624.333 | O91: 26 | P91: 20 | Q91: male | R91: monthly | S91: 41654 | T91: =IF(kiva_loans__muestra[[#This Row],[loan_amount]]>5000,"Alto","Bajo") -> Bajo | U91: =VLOOKUP(kiva_loans__muestra[[#This Row],[country]],Pais!A:B,2,FALSE) -> Rest of Europe | V91: 👨‍🦰M
A92: 657872 | B92: 750 | C92: 750 | D92: Higher education costs | E92: Education | F92: to pay for university tuition | G92: AM | H92: Armenia | I92: Yerevan | J92: AMD | K92: 1690 | L92: 41655.316 | M92: 41626.333 | N92: 41655.904 | O92: 14 | P92: 29 | Q92: female | R92: monthly | S92: 41655 | T92: =IF(kiva_loans__muestra[[#This Row],[loan_amount]]>5000,"Alto","Bajo") -> Bajo | U92: =VLOOKUP(kiva_loans__muestra[[#This Row],[country]],Pais!A:B,2,FALSE) -> Rest of Europe | V92: 👩 F
A93: 657880 | B93: 625 | C93: 625 | D93: Farming | E93: Agriculture | F93: to buy hay for his farm cattle | G93: AM | H93: Armenia | I93: Dilijan | J93: AMD | K93: 1460 | L93: 41655.327 | M93: 41625.333 | N93: 41664.01 | O93: 18 | P93: 24 | Q93: female | R93: monthly | S93: 41655 | T93: =IF(kiva_loans__muestra[[#This Row],[loan_amount]]>5000,"Alto","Bajo") -> Bajo | U93: =VLOOKUP(kiva_loans__muestra[[#This Row],[country]],Pais!A:B,2,FALSE) -> Rest of Europe | V93: 👩 F
A94: 657881 | B94: 1450 | C94: 2500 | D94: Agriculture | E94: Agriculture | F94: to pay for renovation of the greenhouse | G94: AM | H94: Armenia | I94: Malishka village | J94: USD | K94: 1690 | L94: 41655.329 | M94: 41625.333 | O94: 26 | P94: 40 | Q94: female | R94: monthly | S94: 41655 | T94: =IF(kiva_loans__muestra[[#This Row],[loan_amount]]>5000,"Alto","Bajo") -> Bajo | U94: =VLOOKUP(kiva_loans__muestra[[#This Row],[country]],Pais!A:B,2,FALSE) -> Rest of Europe | V94: 👩 F
A95: 657889 | B95: 2300 | C95: 2300 | D95: Agriculture | E95: Agriculture | F95: to pay for two cows and forage for feeding the livestock | G95: AM | H95: Armenia | I95: Jermuk town, Vayots Dzor region | J95: USD | K95: 1690 | L95: 41655.338 | M95: 41627.333 | N95: 41663.52 | O95: 26 | P95: 69 | Q95: female | R95: monthly | S95: 41655 | T95: =IF(kiva_loans__muestra[[#This Row],[loan_amount]]>5000,"Alto","Bajo") -> Bajo | U95: =VLOOKUP(kiva_loans__muestra[[#This Row],[country]],Pais!A:B,2,FALSE) -> Rest of Europe | V95: 👩 F
A96: 657905 | B96: 450 | C96: 2500 | D96: Fruits & Vegetables | E96: Food | F96: to pay for fruits and vegetables to sell in his store. | G96: AM | H96: Armenia | I96: Vanadzor town | J96: USD | K96: 1690 | L96: 41655.353 | M96: 41625.333 | O96: 27 | P96: 9 | Q96: female | R96: monthly | S96: 41655 | T96: =IF(kiva_loans__muestra[[#This Row],[loan_amount]]>5000,"Alto","Bajo") -> Bajo | U96: =VLOOKUP(kiva_loans__muestra[[#This Row],[country]],Pais!A:B,2,FALSE) -> Rest of Europe | V96: 👩 F
A97: 657916 | B97: 2000 | C97: 2000 | D97: Farming | E97: Agriculture | F97: to pay for seeds, sheep and forage for feeding the livestock | G97: AM | H97: Armenia | I97: Tsaghkaber village, Lori region | J97: USD | K97: 1690 | L97: 41655.363 | M97: 41626.333 | N97: 41662.546 | O97: 27 | P97: 61 | Q97: female | R97: monthly | S97: 41655 | T97: =IF(kiva_loans__muestra[[#This Row],[loan_amount]]>5000,"Alto","Bajo") -> Bajo | U97: =VLOOKUP(kiva_loans__muestra[[#This Row],[country]],Pais!A:B,2,FALSE) -> Rest of Europe | V97: 👩 F
A98: 657920 | B98: 550 | C98: 1500 | D98: Agriculture | E98: Agriculture | F98: to pay for forage for feeding the livestock. | G98: AM | H98: Armenia | I98: Gogaran village, Lori region | J98: USD | K98: 1690 | L98: 41655.368 | M98: 41627.333 | O98: 27 | P98: 10 | Q98: female | R98: monthly | S98: 41655 | T98: =IF(kiva_loans__muestra[[#This Row],[loan_amount]]>5000,"Alto","Bajo") -> Bajo | U98: =VLOOKUP(kiva_loans__muestra[[#This Row],[country]],Pais!A:B,2,FALSE) -> Rest of Europe | V98: 👩 F
A99: 657946 | B99: 1500 | C99: 1500 | D99: Livestock | E99: Agriculture | F99: to pay for two cows | G99: AM | H99: Armenia | I99: Kurtan village | J99: USD | K99: 1690 | L99: 41655.399 | M99: 41627.333 | N99: 41661.728 | O99: 38 | P99: 55 | Q99: male | R99: monthly | S99: 41655 | T99: =IF(kiva_loans__muestra[[#This Row],[loan_amount]]>5000,"Alto","Bajo") -> Bajo | U99: =VLOOKUP(kiva_loans__muestra[[#This Row],[country]],Pais!A:B,2,FALSE) -> Rest of Europe | V99: 👨‍🦰M
A100: 657961 | B100: 3000 | C100: 3000 | D100: Livestock | E100: Agriculture | F100: to purchase four cows | G100: AM | H100: Armenia | I100: Katnaghbyur village, Aragatsotn region | J100: USD | K100: 1690 | L100: 41655.412 | M100: 41625.333 | N100: 41683.854 | O100: 26 | P100: 103 | Q100: female | R100: monthly | S100: 41655 | T100: =IF(kiva_loans__muestra[[#This Row],[loan_amount]]>5000,"Alto","Bajo") -> Bajo | U100: =VLOOKUP(kiva_loans__muestra[[#This Row],[country]],Pais!A:B,2,FALSE) -> Rest of Europe | V100: 👩 F
...

Sheet Dashboard

Sheet Pais
A1: Country | B1: Continente | C1: País o territorio
A2: =E2 -> Afganistan | B2: Asia | C2: AFGANISTAN | D2: =LOWER(C2) -> afganistan | E2: =PROPER(D2) -> Afganistan
A3: =E3 -> Albania | B3: Rest of Europe | C3: Albania | D3: =LOWER(C3) -> albania | E3: =PROPER(D3) -> Albania
A4: =E4 -> Alemania | B4: European Union | C4: ALEMANIA | D4: =LOWER(C4) -> alemania | E4: =PROPER(D4) -> Alemania
A5: =E5 -> Andorra | B5: Rest of Europe | C5: ANDORRA | D5: =LOWER(C5) -> andorra | E5: =PROPER(D5) -> Andorra
A6: =E6 -> Angola | B6: Africa | C6: ANGOLA | D6: =LOWER(C6) -> angola | E6: =PROPER(D6) -> Angola
A7: =E7 -> Anguilla | B7: Central America | C7: ANGUILLA | D7: =LOWER(C7) -> anguilla | E7: =PROPER(D7) -> Anguilla
A8: =E8 -> Antigua Y Barbuda | B8: Central America | C8: ANTIGUA Y BARBUDA | D8: =LOWER(C8) -> antigua y barbuda | E8: =PROPER(D8) -> Antigua Y Barbuda
A9: =E9 -> Antillas Holandesas | B9: Central America | C9: ANTILLAS HOLANDESAS | D9: =LOWER(C9) -> antillas holandesas | E9: =PROPER(D9) -> Antillas Holandesas
A10: =E10 -> Arabia Saudi | B10: Asia | C10: ARABIA SAUDI | D10: =LOWER(C10) -> arabia saudi | E10: =PROPER(D10) -> Arabia Saudi
A11: =E11 -> Argelia | B11: Africa | C11: ARGELIA | D11: =LOWER(C11) -> argelia | E11: =PROPER(D11) -> Argelia
A12: =E12 -> Argentina | B12: South America | C12: ARGENTINA | D12: =LOWER(C12) -> argentina | E12: =PROPER(D12) -> Argentina
A13: =E13 -> Armenia | B13: Rest of Europe | C13: Armenia | D13: =LOWER(C13) -> armenia | E13: =PROPER(D13) -> Armenia
... A250: =E250 -> Kosovo | B250: Rest of Europe | C250: Kosovo | D250: =LOWER(C250) -> kosovo | E250: =PROPER(D250) -> Kosovo
